{"cameraMode":{"drawMode":0,"name":"Shaded","section":"Shading Mode"},"sceneLighting":true,"audioPlay":false,"sceneViewState":{"m_AlwaysRefresh":false,"showFog":true,"showSkybox":true,"showFlares":true,"showImageEffects":true,"showParticleSystems":true,"showVisualEffectGraphs":true,"m_FxEnabled":true},"in2DMode":false,"pivot":{"x":-1.4907848834991456,"y":3.989874839782715,"z":-59.258548736572269},"rotation":{"x":0.25656867027282717,"y":-0.01449726801365614,"z":0.0038488309364765884,"w":0.9664103984832764},"size":2.5090720653533937,"orthographic":false}